st_moe_pytorch/__init__.py
st_moe_pytorch/distributed.py
st_moe_pytorch/st_moe_pytorch.py
st_moe_pytorch-0.1.8.dist-info/LICENSE
st_moe_pytorch-0.1.8.dist-info/METADATA
st_moe_pytorch-0.1.8.dist-info/WHEEL
st_moe_pytorch-0.1.8.dist-info/top_level.txt
st_moe_pytorch-0.1.8.dist-info/RECORD
