Metadata-Version: 2.1
Name: st-moe-pytorch
Version: 0.1.8
Summary: ST - Mixture of Experts - Pytorch
Home-page: https://github.com/lucidrains/st-moe-pytorch
Author: Phil Wang
Author-email: lucidrains@gmail.com
License: MIT
Keywords: artificial intelligence,deep learning,mixture of experts
Classifier: Development Status :: 4 - Beta
Classifier: Intended Audience :: Developers
Classifier: Topic :: Scientific/Engineering :: Artificial Intelligence
Classifier: License :: OSI Approved :: MIT License
Classifier: Programming Language :: Python :: 3.6
License-File: LICENSE
Requires-Dist: beartype
Requires-Dist: CoLT5-attention >=0.10.15
Requires-Dist: einops >=0.6
Requires-Dist: torch >=2.0
